<?xml version="1.0" encoding="GBK" ?>
<TRANSACTION RIGHTS="00000000" TITLE="5613 拆分票据票款收回"
  xmlns="http://www.otd.org/MENU" xmlns:W3CNS="http://www.w3c.org">
<COMMSEND>"{

	initfd();
    $MSGTYPE='03001';
    $TXNO='9986';
    $FD12 = '4344';
	$FD63 = #ZYNUM;
	$FD67 = #HKFLAG;
    callserver();
    if($FD12!='0000'){
        showmsg(geterror());
        return(false);
    }
    $FD16 = '4344';
    $MSGTYPE='03001';

}"
</COMMSEND>
<COMMRECV>"{
}"
</COMMRECV>
<VARIABLE>
  <ITEM LINE="3"  COL="3" TYPE="%-60s" FUNCTIONS=
    "T(5613                            拆分票据票款收回)"/>
  <ITEM LINE="4"  COL="3"  TYPE="%-74s" FUNCTIONS=
   "T(─────────────────────────────────────)"/>
  <PAGE NAME="DEFAULT">

  <ITEM NAME="#TXNO" TYPE="%-4s" FUNCTIONS="T($TXNO=4344)"/>
  <ITEM NAME="#MSGTYPE" TYPE="%-5s" FUNCTIONS="T($MSGTYPE=03001)"/>

  <ITEM LINE="7"  COL="5"  TYPE="%-10s" FUNCTIONS="T(还款类型:!)"/>
  <ITEM LINE="9"  COL="5"  TYPE="%-10s" FUNCTIONS="T(质押编号:)"/>

  <ITEM LINE="11"  COL="13"  TYPE="%-60s" FUNCTIONS=
	   "T(-------------------- 以下为回显信息 ---------------------)"/>
  <ITEM LINE="13" COL="5"  TYPE="%-12s" FUNCTIONS="T(票据类型:!)"/>
  <ITEM LINE="14" COL="5"  TYPE="%-12s" FUNCTIONS="T(票 据 号:)"/>
  <ITEM LINE="15" COL="5"  TYPE="%-12s" FUNCTIONS="T(票面金额:)"/>
  <ITEM LINE="16" COL="5"  TYPE="%-12s" FUNCTIONS="T(保证金帐号:)"/>

<!-- 定义callserver返回但界面不用的变量 -->
  <ITEM TYPE="%17.2f" NAME="#FD100_1"  FUNCTIONS="V(NB)J(#XFD100_1)"/>
  <ITEM NAME="#XFD100_1" TYPE="%-16s"  FUNCTIONS="X(#FD100_1)"/>
  <ITEM TYPE="%17.2f" NAME="#FD100_2"  FUNCTIONS="V(NB)J(#XFD100_2)"/>
  <ITEM NAME="#XFD100_2" TYPE="%-16s"  FUNCTIONS="X(#FD100_2)"/>
  <ITEM TYPE="%17.2f" NAME="#FD100_3"  FUNCTIONS="V(NB)J(#XFD100_3)"/>
  <ITEM NAME="#XFD100_3" TYPE="%-16s"  FUNCTIONS="X(#FD100_3)"/>

  <ITEM TYPE="%17.2f" NAME="#FD100_4"  FUNCTIONS="V(NB)J(#XFD100_4)"/>
  <ITEM NAME="#XFD100_4" TYPE="%-16s"  FUNCTIONS="X(#FD100_4)"/>

  <ITEM TYPE="%9.6f"  NAME="#FD100_5"  FUNCTIONS="V(NB)J(#XFD100_5)"/>
  <ITEM NAME="#XFD100_5" TYPE="%-8s"   FUNCTIONS="X(#FD100_5)"/>

  <ITEM TYPE="%-2s"   NAME="#FD100_6"  FUNCTIONS="V(NB)"/>
  <ITEM TYPE="%-2s"   NAME="#FD100_7"  FUNCTIONS="V(NB)"/>
  <ITEM TYPE="%-10s"  NAME="#FD100_8"  FUNCTIONS="V(NB)"/>
  <ITEM TYPE="%-10s"  NAME="#FD100_9"  FUNCTIONS="V(NB)"/>
  <ITEM TYPE="%17.2f" NAME="#FD100_10" FUNCTIONS="V(NB)J(#XFD100_10)"/>
  <ITEM NAME="#XFD100_10" TYPE="%-16s" FUNCTIONS="X(#FD100_10)"/>

  <ITEM TYPE="%-2s" NAME="#CURCD"  FUNCTIONS="T(01)"/>  <!-- 9910,$FD21 -->

  <ITEM LINE="7"  COL="15" TYPE="%-16s" NAME="#HKFLAG" DEVICE="KEYBOARD" FUNCTIONS="V(NB)">
    <SELECT LINE="0" COL="0">
        <OPTION VALUE="1" TITLE="同城"/>
        <OPTION VALUE="2" TITLE="大额"/>
    </SELECT>
  </ITEM>
  <ITEM LINE="9" COL="15" TYPE="%-12s"  NAME="#ZYNUM" DEVICE="KEYBOARD" FUNCTIONS="">
  <ONLOSTFOCUS>
    "{
        dim @baktxno as string;
        @baktxno=$TXNO;
        $TXNO='9985';
        $FD63 = #ZYNUM;
        commsend_001();
        callserver();
        $TXNO=@baktxno;
        if($FD12!='0000'){
            showmsg(geterror());
            return(false);
        }
		#BZJACTNO=$FD33;
		#PJNUM=$FD60;
		#PJTYPE=$FD90;
		setitems('#FD100_1#PMAVBAL#FD100_3#FD100_4#FD100_5#FD100_6#FD100_7#FD100_8#FD100_9#FD100_10',$FD100);

    }"
  </ONLOSTFOCUS>
  </ITEM>


  <ITEM LINE="13" COL="17" TYPE="%-3s"  NAME="#PJTYPE" INPUT="LABEL" DEVICE="KEYBOARD" FUNCTIONS="">
    <SELECT LINE="0" COL="0">
        <OPTION VALUE="111" TITLE="银行承兑汇票"/>
        <OPTION VALUE="112" TITLE="商业承兑汇票"/>
    </SELECT>
  </ITEM>

  <ITEM LINE="14" COL="17" TYPE="%-16s" NAME="#PJNUM"  INPUT="LABEL"  DEVICE="KEYBOARD" FUNCTIONS=""/>
  <ITEM LINE="15" COL="17" NAME="#XPMAVBAL" TYPE="%-16s" FUNCTIONS="X(#PMAVBAL)"/>
  <ITEM TYPE="%17.2f" NAME="#PMAVBAL" FUNCTIONS="J(#XPMAVBAL)"/>
  <ITEM LINE="16" COL="17" TYPE="%-50s"  NAME="#BZJACTNO"    INPUT="LABEL" FUNCTIONS="">
  <ONLOSTFOCUS>
  "{
        if(#HKFLAG== '2')
        {
			goitem(#THIRD_PAGE,false);
        }
  }"
  </ONLOSTFOCUS>
  </ITEM>


  <ITEM LINE="21" COL="49" NAME="#THIRD_PAGE" TYPE="%-6s" FUNCTIONS="T(下一页)" INPUT="BUTTON">
    <ONCLICK>"{
        loadpage('PAGE3');
    }"
    </ONCLICK>
  </ITEM>
  </PAGE>

  <PAGE NAME="PAGE3">
  <BLOCK NAME="5801_HV" LINE="6" COL="5" VISABLE="FALSE">
     <IMPORT>5801_HV.IMP</IMPORT>
  </BLOCK>

  <ITEM LINE="21" COL="49"  TYPE="%-6s" FUNCTIONS="T(上一页)" INPUT="BUTTON">
    <ONCLICK>"{
        loadpage('DEFAULT');
        }"
    </ONCLICK>
  </ITEM>
  </PAGE>

  <!--输出变量--->

  <!------------一些没有用的变量,只是为了公共脚本执行时不报错------------>
  <ITEM NAME="#PASSWD" TYPE="%-6s" FUNCTIONS="T()"/>
  
  <ITEM LINE="21" COL="59"  TYPE="%-6s" FUNCTIONS="T(确  定)" INPUT="SUBMIT"/>

</VARIABLE>
<REQUEST>
</REQUEST>

<RESPONSE>
<PACKAGE DEVICE="SCREEN" DESC="显示内容">
NOTHING
</PACKAGE>
<PRINT>
"{
    print(3,20,'交易成功!');
}"
</PRINT>

</RESPONSE>

</TRANSACTION>
