<?xml version="1.0" encoding="GBK" ?>
<TRANSACTION RIGHTS="11001000" TITLE="8108    个人代理编号查询"
  xmlns="http://www.otd.org/MENU" xmlns:W3CNS="http://www.w3c.org">
<COMMSEND>"{
			commsend_001();		
		  $FD27=#GRNAME;
     	$FD31=#GRACTNO;
     	$FD63=#AGENTID;
     	$FD70=#CIRTIFTYPE;
     	$FD60=#CIRTIFNUM;
     	$FD92=#DWID;
}"
</COMMSEND>
<COMMRECV>"{

}"
</COMMRECV>

<VARIABLE>
  <ITEM LINE="3"  COL="3" TYPE="%-52s" FUNCTIONS=
    "T(8108                           个人代理编号查询)"/>
  <ITEM LINE="4"  COL="3"  TYPE="%-74s" FUNCTIONS=
   "T(─────────────────────────────────────)"/>
  <ITEM NAME="#TXNO" TYPE="%-4s" FUNCTIONS="T($TXNO=6108)"/>
  <ITEM NAME="#MSGTYPE" TYPE="%-5s" FUNCTIONS="T($MSGTYPE=03001)"/>
  
  <ITEM LINE="7"   COL="10"   TYPE="%-13s" FUNCTIONS="T(个人代理编号:)"/>
  <ITEM LINE="9"   COL="10"   TYPE="%-13s" FUNCTIONS="T(个人    账号:)"/>
  <ITEM LINE="11"  COL="10"   TYPE="%-13s" FUNCTIONS="T(个人    名称:)" />
  <ITEM LINE="13"  COL="10"   TYPE="%-13s" FUNCTIONS="T(单位    编号:)"/>
  <ITEM LINE="15"  COL="10"   TYPE="%-13s" FUNCTIONS="T(证件    类型:!)"/>
  <ITEM LINE="16"  COL="10"   TYPE="%-13s" FUNCTIONS="T(证件    号码:)"/>
  
  <ITEM LINE="7"   COL="24"  NAME="#AGENTID"        TYPE="%-20s"        INPUT="TEXT"    FUNCTIONS=""/>
  <ITEM LINE="9"   COL="24"  NAME="#GRACTNO" TYPE="%-24s" INPUT="TEXT" FUNCTIONS=""/>  	
  <ITEM LINE="11"  COL="24"  NAME="#GRNAME"      TYPE="%-40s"       INPUT="TEXT"     FUNCTIONS=""/>
  <ITEM LINE="13"  COL="24"  NAME="#DWID"        TYPE="%-4s"        INPUT="TEXT"    FUNCTIONS=""/>
  <ITEM LINE="15"  COL="24"  NAME="#CIRTIFTYPE"  TYPE="%-1s"        INPUT="SELECT"   FUNCTIONS="">
    <SELECT>
					<OPTION VALUE="1" TITLE="1.身份证"/>
					<OPTION VALUE="2" TITLE="2.户口薄"/>
					<OPTION VALUE="3" TITLE="3.护照"/>
					<OPTION VALUE="4" TITLE="4.军官证"/>
					<OPTION VALUE="5" TITLE="5.回乡证"/>
					<OPTION VALUE="6" TITLE="6.士兵证"/>
					<OPTION VALUE="7" TITLE="7.港澳居民来往通行证"/>
					<OPTION VALUE="E" TITLE="E.临时身份证"/>
					<OPTION VALUE="F" TITLE="F.外国人居留证"/>
					<OPTION VALUE="G" TITLE="G.警官证"/>
					<OPTION VALUE="H" TITLE="H.其他证件"/>
					<OPTION VALUE="I" TITLE="I.台湾同胞来往通行证"/>
    </SELECT>
  </ITEM>
  <ITEM LINE="16" COL="24" TYPE="%-20s" NAME="#CIRTIFNUM"INPUT="TEXT" FUNCTIONS=""/>
	 <!------------一些没有用的变量,只是为了公共脚本执行时不报错------------>
  <ITEM NAME="#PASSWD" TYPE="%-6s" FUNCTIONS="T()"/>
  <ITEM LINE="20"  COL="59" TYPE="%-6s" FUNCTIONS="T(确  定)" INPUT="SUBMIT"/>
</VARIABLE>
<REQUEST>
</REQUEST>
<RESPONSE>
<!---
<PACKAGE DEVICE="PRINTER" DESC="请插入打印凭条!">
 NOTHING
 </PACKAGE>
  <PRINT>"{ 
          if($FD67=='0')
          {
            #DWSTS='正常';
          }
          else
          {
           	#DWSTS='异常';
          }
                                print( 3,	 30,'[7      ]   [30]',$KINBR,$BRNAME);
                                print( 4,	 30,'单位资料查询');
	  			print( 5,  15,'交易日期:[8]',$HDATE);  
	  			print( 6,  15,'单位账号:[24 ]',#ACTNO);
	                	print( 5, 20,'机构名称:[30]',$BRNAME);	
                                print( 5, 2,'代码:8108');	
                                print( 5, 13,'交易: 个人代理编号查询');
                                print( 7,  20,'单位编号:[4   ]  单位名称:[40 ]',#DWID,#DWNAME);
	  			print( 8,  20,'建立机构:[5    ] 建立柜员:[4    ]',$FD91,$FD49);
	  			print( 9,  20,'业务类型:[4   ]  代理类型:[20 ]',#YWNAME,#AGENTNAME);
	  			print( 10, 20 ,'操作员号:[4   ]  单位状态:[4  ]  ',$FD7,#DWSTS);  
                        	print( 24, 20,'备注:')
                                print( 24, 27,'交易日期:[8] [8]',$HDATE,@txtime);
                                print( 24, 5,'柜员:[4]',$FD7);
                                print( 24, 5,'流水号:[6]',$FD4);

           }"
</PRINT>
--->
</RESPONSE>
</TRANSACTION>
